jinf/__init__.py
jinf/data/e_basic_stem_suffix.json
jinf/data/jinf.json
jinf/jinf.py
jinf-1.0.4.dist-info/LICENSE
jinf-1.0.4.dist-info/WHEEL
jinf-1.0.4.dist-info/METADATA
jinf-1.0.4.dist-info/RECORD
