Metadata-Version: 2.1
Name: jinf
Version: 1.0.4
Summary: A Japanese inflection converter.
Home-page: https://github.com/hkiyomaru/jinf
License: MIT
Keywords: NLP,JUMAN
Author: Hirokazu Kiyomaru
Author-email: h.kiyomaru@gmail.com
Requires-Python: >=3.8,<4.0
Classifier: License :: OSI Approved :: MIT License
Classifier: Programming Language :: Python :: 3
Classifier: Programming Language :: Python :: 3.10
Classifier: Programming Language :: Python :: 3.8
Classifier: Programming Language :: Python :: 3.9
Provides-Extra: pyknp
Requires-Dist: pyknp[pyknp] (>=0.6,<1.0); extra == "pyknp"
Project-URL: Repository, https://github.com/hkiyomaru/jinf
